[{"Users":[{"Username":"Andrei","UserType":"Super","Groups":["Global","KoolKids"]},{"Username":"Jeff","UserType":"Group","Groups":["Global","KoolKids","Bros"]},{"Username":"Greg","UserType":"Normie","Groups":["Global","Bros"]}]},{"Groups":[{"Group":"Global","Users":["Andrei","Jeff","Greg"],"Channels":["Four","One"]},{"Group":"KoolKids","Users":["Andrei","Jeff"],"Channels":["Two"]},{"Group":"Bros","Users":["Jeff","Greg"],"Channels":["Three"]}]},{"Channels":[{"Channel":"Global:Four","Users":["Andrei","Greg","Jeff"],"Data":[]},{"Channel":"Global:One","Users":["Andrei","Jeff","Greg"],"Data":[]},{"Channel":"KoolKids:Two","Users":["Andrei","Jeff"],"Data":[]},{"Channel":"Bros:Three","Users":["Jeff","Greg"],"Data":[]}]}]